streamlit_nivo_sankey/__init__.py
streamlit_nivo_sankey/frontend/build/asset-manifest.json
streamlit_nivo_sankey/frontend/build/bootstrap.min.css
streamlit_nivo_sankey/frontend/build/index.html
streamlit_nivo_sankey/frontend/build/static/js/main.fc4a5a57.js
streamlit_nivo_sankey/frontend/build/static/js/main.fc4a5a57.js.LICENSE.txt
streamlit_nivo_sankey/frontend/build/static/js/main.fc4a5a57.js.map
streamlit_nivo_sankey-1.0.0.dist-info/LICENSE
streamlit_nivo_sankey-1.0.0.dist-info/METADATA
streamlit_nivo_sankey-1.0.0.dist-info/WHEEL
streamlit_nivo_sankey-1.0.0.dist-info/top_level.txt
streamlit_nivo_sankey-1.0.0.dist-info/RECORD
