Metadata-Version: 2.1
Name: streamlit_nivo_sankey
Version: 1.0.0
Summary: A Streamlit component for Nivo Sankey diagrams.
Home-page: 
Author: Zhixuan Qi
Author-email: zhixuanqi@outlook.com
Requires-Python: >=3.7
License-File: LICENSE
Requires-Dist: streamlit>=0.63
Provides-Extra: devel
Requires-Dist: wheel; extra == "devel"
Requires-Dist: pytest==7.4.0; extra == "devel"
Requires-Dist: playwright==1.39.0; extra == "devel"
Requires-Dist: requests==2.31.0; extra == "devel"
Requires-Dist: pytest-playwright-snapshot==1.0; extra == "devel"
Requires-Dist: pytest-rerunfailures==12.0; extra == "devel"
